limes/__init__.py
limes/errors.py
limes/models.py
limes/protocols.py
limes/py.typed
limes/sentence.py
limes/text.py
limes/analyzers/__init__.py
limes/analyzers/base.py
limes/analyzers/interfaces.py
limes/analyzers/mixins.py
limes/analyzers/models.py
limes/analyzers/de/__init__.py
limes/analyzers/de/barrier_analyzer.py
limes/analyzers/de/barriers.py
limes/analyzers/de/complexity_analyzer.py
limes/analyzers/de/lexicon.py
limes/analyzers/de/resources/__init__.py
limes/analyzers/de/resources/regular_expressions.py
limes/analyzers/de/resources/word_lists.py
limes/data/de/lexicon.marisa
limes/parsers/__init__.py
limes/parsers/interfaces.py
limes/parsers/spacy_parser.py
lang_limes-0.1.3.dist-info/METADATA
lang_limes-0.1.3.dist-info/WHEEL
lang_limes-0.1.3.dist-info/licenses/LICENSES/Apache-2.0.txt
lang_limes-0.1.3.dist-info/RECORD
