Metadata-Version: 2.4
Name: lang-limes
Version: 0.1.3
Summary: Linguistic Identification of Morphosyntactic and Expressive Snags
Project-URL: documentation, https://deepsight.codeberg.page/LIMES/
Project-URL: source, https://codeberg.org/deepsight/LIMES/
Author-email: deepsight GmbH <hi@deepsight.de>
Maintainer-email: Jannik Schmitt <jannik.schmitt@deepsight.de>
License-Expression: Apache-2.0
License-File: LICENSES/Apache-2.0.txt
Requires-Python: >=3.12
Requires-Dist: marisa-trie>=1.3.1
Requires-Dist: numpy>=2.4.1
Requires-Dist: pydantic>=2.12.5
Requires-Dist: spacy>=3.8.11
